drawings_for_3D_printing/serial_weighing_scale.stl
drawings_for_3D_printing/serial_weighing_scale__case_base.stl
drawings_for_3D_printing/serial_weighing_scale__case_main.stl
drawings_for_3D_printing/serial_weighing_scale__model_arduino_uno.stl
drawings_for_3D_printing/serial_weighing_scale__model_load_cell.stl
drawings_for_3D_printing/serial_weighing_scale__model_standoffs.stl
drawings_for_3D_printing/serial_weighing_scale__platform.stl
drawings_for_3D_printing/serial_weighing_scale__platform_edge_overhang.stl
drawings_for_3D_printing/serial_weighing_scale__platform_spacer.stl
drawings_for_3D_printing/serial_weighing_scale__step_files.zip
scale_firmware/scale_firmware.ino
serial_weighing_scale/__init__.py
serial_weighing_scale/connection.py
serial_weighing_scale/scale.py
serial_weighing_scale-2.0.4.dist-info/licenses/LICENSE
tests/minimal_usage.py
tests/tests/test_integration/test_placeholder.py
tests/tests/test_unit/test_unit.py
serial_weighing_scale-2.0.4.dist-info/METADATA
serial_weighing_scale-2.0.4.dist-info/WHEEL
serial_weighing_scale-2.0.4.dist-info/top_level.txt
serial_weighing_scale-2.0.4.dist-info/RECORD
