Metadata-Version: 2.4
Name: serial_weighing_scale
Version: 2.0.4
Summary: serial_weighing_scale: Python API for serial weighing scales based on Arduino+HX711
Author-email: "Lars B. Rollik" <L.B.Rollik@protonmail.com>
License: BSD 3-Clause License
Project-URL: Repository, https://github.com/larsrollik/serial-weighing-scale
Project-URL: Issue Tracker, https://github.com/larsrollik/serial-weighing-scale/issues
Classifier: Intended Audience :: Developers
Classifier: Topic :: Software Development :: Libraries :: Python Modules
Classifier: License :: OSI Approved :: BSD License
Classifier: Operating System :: OS Independent
Classifier: Programming Language :: Python
Classifier: Programming Language :: Python :: 3
Classifier: Programming Language :: Python :: 3.6
Classifier: Programming Language :: Python :: 3.7
Classifier: Programming Language :: Python :: 3.8
Classifier: Programming Language :: Python :: 3.9
Classifier: Programming Language :: Python :: 3.10
Classifier: Programming Language :: Python :: 3.11
Classifier: Programming Language :: Python :: 3.12
Requires-Python: >=3.6
License-File: LICENSE
Requires-Dist: pyserial
Provides-Extra: dev
Requires-Dist: black; extra == "dev"
Requires-Dist: bump2version; extra == "dev"
Requires-Dist: pytest-cov; extra == "dev"
Requires-Dist: pre-commit; extra == "dev"
Requires-Dist: toml; extra == "dev"
Requires-Dist: types-PyYAML; extra == "dev"
Dynamic: license-file
